CHANGELOG.txt
LICENCE.txt
MANIFEST.in
README.txt
setup.py
/home/carlinhoshk/dev/pythonce/pythonce/calculator/cal.c
/home/carlinhoshk/dev/pythonce/pythonce/ola/ola.c
/home/carlinhoshk/dev/pythonce/pythonce/ola/wrap_ola.c
env/lib/python3.10/site-packages/cython.py
env/lib/python3.10/site-packages/Cython/CodeWriter.py
env/lib/python3.10/site-packages/Cython/Coverage.py
env/lib/python3.10/site-packages/Cython/Debugging.py
env/lib/python3.10/site-packages/Cython/Shadow.py
env/lib/python3.10/site-packages/Cython/StringIOTree.py
env/lib/python3.10/site-packages/Cython/TestUtils.py
env/lib/python3.10/site-packages/Cython/Utils.py
env/lib/python3.10/site-packages/Cython/__init__.py
env/lib/python3.10/site-packages/Cython-0.29.35.dist-info/COPYING.txt
env/lib/python3.10/site-packages/Cython-0.29.35.dist-info/LICENSE.txt
env/lib/python3.10/site-packages/Cython-0.29.35.dist-info/entry_points.txt
env/lib/python3.10/site-packages/Cython-0.29.35.dist-info/top_level.txt
env/lib/python3.10/site-packages/Cython/Build/BuildExecutable.py
env/lib/python3.10/site-packages/Cython/Build/Cythonize.py
env/lib/python3.10/site-packages/Cython/Build/Dependencies.py
env/lib/python3.10/site-packages/Cython/Build/Distutils.py
env/lib/python3.10/site-packages/Cython/Build/Inline.py
env/lib/python3.10/site-packages/Cython/Build/IpythonMagic.py
env/lib/python3.10/site-packages/Cython/Build/__init__.py
env/lib/python3.10/site-packages/Cython/Build/Tests/TestCyCache.py
env/lib/python3.10/site-packages/Cython/Build/Tests/TestInline.py
env/lib/python3.10/site-packages/Cython/Build/Tests/TestIpythonMagic.py
env/lib/python3.10/site-packages/Cython/Build/Tests/TestStripLiterals.py
env/lib/python3.10/site-packages/Cython/Build/Tests/__init__.py
env/lib/python3.10/site-packages/Cython/Compiler/AnalysedTreeTransforms.py
env/lib/python3.10/site-packages/Cython/Compiler/Annotate.py
env/lib/python3.10/site-packages/Cython/Compiler/AutoDocTransforms.py
env/lib/python3.10/site-packages/Cython/Compiler/Buffer.py
env/lib/python3.10/site-packages/Cython/Compiler/Builtin.py
env/lib/python3.10/site-packages/Cython/Compiler/CmdLine.py
env/lib/python3.10/site-packages/Cython/Compiler/Code.py
env/lib/python3.10/site-packages/Cython/Compiler/CodeGeneration.py
env/lib/python3.10/site-packages/pip-22.0.2.dist-info/LICENSE.txt
env/lib/python3.10/site-packages/pip-22.0.2.dist-info/entry_points.txt
env/lib/python3.10/site-packages/pip-22.0.2.dist-info/top_level.txt
env/lib/python3.10/site-packages/pythonce-0.0.0-py3.10-linux-x86_64.egg/EGG-INFO/SOURCES.txt
env/lib/python3.10/site-packages/pythonce-0.0.0-py3.10-linux-x86_64.egg/EGG-INFO/dependency_links.txt
env/lib/python3.10/site-packages/pythonce-0.0.0-py3.10-linux-x86_64.egg/EGG-INFO/native_libs.txt
env/lib/python3.10/site-packages/pythonce-0.0.0-py3.10-linux-x86_64.egg/EGG-INFO/top_level.txt
env/lib/python3.10/site-packages/pythonce-0.0.7-py3.10-linux-x86_64.egg/EGG-INFO/SOURCES.txt
env/lib/python3.10/site-packages/pythonce-0.0.7-py3.10-linux-x86_64.egg/EGG-INFO/dependency_links.txt
env/lib/python3.10/site-packages/pythonce-0.0.7-py3.10-linux-x86_64.egg/EGG-INFO/native_libs.txt
env/lib/python3.10/site-packages/pythonce-0.0.7-py3.10-linux-x86_64.egg/EGG-INFO/top_level.txt
env/lib/python3.10/site-packages/setuptools-59.6.0.dist-info/entry_points.txt
env/lib/python3.10/site-packages/setuptools-59.6.0.dist-info/top_level.txt
env/lib/python3.10/site-packages/wheel-0.40.0.dist-info/LICENSE.txt
env/lib/python3.10/site-packages/wheel-0.40.0.dist-info/entry_points.txt
env/lib64/python3.10/site-packages/Cython-0.29.35.dist-info/COPYING.txt
env/lib64/python3.10/site-packages/Cython-0.29.35.dist-info/LICENSE.txt
env/lib64/python3.10/site-packages/Cython-0.29.35.dist-info/entry_points.txt
env/lib64/python3.10/site-packages/Cython-0.29.35.dist-info/top_level.txt
env/lib64/python3.10/site-packages/pip-22.0.2.dist-info/LICENSE.txt
env/lib64/python3.10/site-packages/pip-22.0.2.dist-info/entry_points.txt
env/lib64/python3.10/site-packages/pip-22.0.2.dist-info/top_level.txt
env/lib64/python3.10/site-packages/pythonce-0.0.0-py3.10-linux-x86_64.egg/EGG-INFO/SOURCES.txt
env/lib64/python3.10/site-packages/pythonce-0.0.0-py3.10-linux-x86_64.egg/EGG-INFO/dependency_links.txt
env/lib64/python3.10/site-packages/pythonce-0.0.0-py3.10-linux-x86_64.egg/EGG-INFO/native_libs.txt
env/lib64/python3.10/site-packages/pythonce-0.0.0-py3.10-linux-x86_64.egg/EGG-INFO/top_level.txt
env/lib64/python3.10/site-packages/pythonce-0.0.7-py3.10-linux-x86_64.egg/EGG-INFO/SOURCES.txt
env/lib64/python3.10/site-packages/pythonce-0.0.7-py3.10-linux-x86_64.egg/EGG-INFO/dependency_links.txt
env/lib64/python3.10/site-packages/pythonce-0.0.7-py3.10-linux-x86_64.egg/EGG-INFO/native_libs.txt
env/lib64/python3.10/site-packages/pythonce-0.0.7-py3.10-linux-x86_64.egg/EGG-INFO/top_level.txt
env/lib64/python3.10/site-packages/setuptools-59.6.0.dist-info/entry_points.txt
env/lib64/python3.10/site-packages/setuptools-59.6.0.dist-info/top_level.txt
env/lib64/python3.10/site-packages/wheel-0.40.0.dist-info/LICENSE.txt
env/lib64/python3.10/site-packages/wheel-0.40.0.dist-info/entry_points.txt
pythonce.egg-info/PKG-INFO
pythonce.egg-info/SOURCES.txt
pythonce.egg-info/dependency_links.txt
pythonce.egg-info/top_level.txt
