Metadata-Version: 2.1
Name: pythonce
Version: 0.0.7
Summary: Python Library writen in C 
Home-page: UNKNOWN
Author: carlinhoshk
Author-email: carlosmdohk@gmail.com
License: MIT
Keywords: c
Platform: UNKNOWN
Classifier: Development Status :: 5 - Production/Stable
Classifier: Intended Audience :: Developers
Classifier: License :: OSI Approved :: MIT License
Classifier: Operating System :: Microsoft :: Windows :: Windows 10
Classifier: Programming Language :: Python :: 3
License-File: LICENCE.txt
